floralab/__init__.py
floralab/cli.py
floralab/ui_server.py
floralab/bin/florago-arm64
floralab/bin/florago-amd64
floralab/templates/dashboard.html
floralab-0.1.0.dist-info/METADATA
floralab-0.1.0.dist-info/WHEEL
floralab-0.1.0.dist-info/entry_points.txt
floralab-0.1.0.dist-info/RECORD
