Metadata-Version: 2.4
Name: floralab
Version: 0.1.0
Summary: Python CLI for interacting with Flower-AI stacks on SLURM via florago
Requires-Python: >=3.12
Requires-Dist: fastapi>=0.121.2
Requires-Dist: flwr[simulation]>=1.23.0
Requires-Dist: httpx>=0.27.0
Requires-Dist: ray>=2.31.0
Requires-Dist: tomli-w>=1.0.0
Requires-Dist: typer>=0.9.0
Requires-Dist: uvicorn>=0.38.0
